aws_ssm/ssm.py
aws_ssm_devlibx-0.0.7.dist-info/LICENSE
aws_ssm_devlibx-0.0.7.dist-info/METADATA
aws_ssm_devlibx-0.0.7.dist-info/WHEEL
aws_ssm_devlibx-0.0.7.dist-info/top_level.txt
aws_ssm_devlibx-0.0.7.dist-info/RECORD
