Metadata-Version: 2.1
Name: aws-ssm-devlibx
Version: 0.0.7
Summary: Python DSL for setting up Flask app CDC
Home-page: https://github.com/devlibx/aws-ssm-py
Author: devlibx
Author-email: devlibxgithub@gmail.com
License: MIT
Platform: UNKNOWN
License-File: LICENSE
Requires-Dist: boto3
